draft_kings/__init__.py
draft_kings/client.py
draft_kings/data.py
draft_kings/http_client.py
draft_kings/output/__init__.py
draft_kings/output/objects/__init__.py
draft_kings/output/objects/contests.py
draft_kings/output/objects/countries.py
draft_kings/output/objects/draft_group.py
draft_kings/output/objects/draftables.py
draft_kings/output/objects/game_type_rules.py
draft_kings/output/objects/players.py
draft_kings/output/objects/regions.py
draft_kings/output/schema/__init__.py
draft_kings/output/schema/contests.py
draft_kings/output/schema/countries.py
draft_kings/output/schema/draft_group.py
draft_kings/output/schema/draftables.py
draft_kings/output/schema/fields.py
draft_kings/output/schema/game_type_rules.py
draft_kings/output/schema/players.py
draft_kings/output/schema/regions.py
draft_kings/output/transformers/__init__.py
draft_kings/output/transformers/contests.py
draft_kings/output/transformers/countries.py
draft_kings/output/transformers/draft_group.py
draft_kings/output/transformers/draftables.py
draft_kings/output/transformers/game_type_rules.py
draft_kings/output/transformers/players.py
draft_kings/output/transformers/regions.py
draft_kings/output/transformers/sports.py
draft_kings/response/__init__.py
draft_kings/response/objects/__init__.py
draft_kings/response/objects/contests.py
draft_kings/response/objects/countries.py
draft_kings/response/objects/draft_group.py
draft_kings/response/objects/draftables.py
draft_kings/response/objects/game_type_rules.py
draft_kings/response/objects/players.py
draft_kings/response/objects/regions.py
draft_kings/response/schema/__init__.py
draft_kings/response/schema/contests.py
draft_kings/response/schema/countries.py
draft_kings/response/schema/draft_group.py
draft_kings/response/schema/draftables.py
draft_kings/response/schema/fields.py
draft_kings/response/schema/game_type_rules.py
draft_kings/response/schema/players.py
draft_kings/response/schema/regions.py
draft_kings/url_builder.py
draft_kings/utilities.py
draft_kings-3.1.0.dist-info/LICENSE
draft_kings-3.1.0.dist-info/WHEEL
draft_kings-3.1.0.dist-info/METADATA
draft_kings-3.1.0.dist-info/RECORD
