Metadata-Version: 2.1
Name: draft-kings
Version: 3.1.0
Summary: A client to access data on draftkings.com
Home-page: https://jaebradley.github.io/draftkings_client
License: MIT
Keywords: Daily Fantasy Sports,DraftKings
Author: Jae Bradley
Author-email: jae.b.bradley@gmail.com
Maintainer: Jae Bradley
Maintainer-email: jae.b.bradley@gmail.com
Requires-Python: >=3.7,<4.0
Classifier: License :: OSI Approved :: MIT License
Classifier: Operating System :: OS Independent
Classifier: Programming Language :: Python :: 3
Classifier: Programming Language :: Python :: 3.7
Classifier: Programming Language :: Python :: 3.8
Classifier: Programming Language :: Python :: 3.9
Requires-Dist: marshmallow (>=3.9.1,<4.0.0)
Requires-Dist: marshmallow-enum (>=1.5.1,<2.0.0)
Requires-Dist: requests (>=2.20.0,<3.0.0)
Project-URL: Documentation, https://jaebradley.github.io/draftkings_client
Project-URL: Repository, https://github.com/jaebradley/draftkings_client
Project-URL: issues, https://github.com/jaebradley/draftkings_client/issues
Project-URL: pull_requests, https://github.com/jaebradley/draftkings_client/pull_requests
